atsphinx/htmx_boost/__init__.py
atsphinx/htmx_boost/py.typed
atsphinx_htmx_boost-0.3.0.dist-info/METADATA
atsphinx_htmx_boost-0.3.0.dist-info/WHEEL
atsphinx_htmx_boost-0.3.0.dist-info/licenses/LICENSE
atsphinx_htmx_boost-0.3.0.dist-info/RECORD
