Metadata-Version: 2.4
Name: atsphinx-htmx-boost
Version: 0.3.0
Summary: Improve user-experience for Sphinx document.
Project-URL: Home, https://github.com/atsphinx/htmx-boost
Project-URL: Repository, https://github.com/atsphinx/htmx-boost
Project-URL: Issues, https://github.com/atsphinx/htmx-boost/issues
Project-URL: Changelog, https://github.com/atsphinx/htmx-boost/blob/main/CHANGES.rst
Author-email: Kazuya Takei <myself@attakei.net>
License-Expression: Apache-2.0
License-File: LICENSE
Classifier: Development Status :: 4 - Beta
Classifier: Framework :: Sphinx
Classifier: Framework :: Sphinx :: Extension
Classifier: Intended Audience :: Developers
Classifier: License :: OSI Approved :: Apache Software License
Classifier: Operating System :: OS Independent
Classifier: Programming Language :: Python
Classifier: Programming Language :: Python :: 3 :: Only
Classifier: Programming Language :: Python :: 3.10
Classifier: Programming Language :: Python :: 3.11
Classifier: Programming Language :: Python :: 3.12
Classifier: Programming Language :: Python :: 3.13
Classifier: Programming Language :: Python :: 3.14
Classifier: Topic :: Documentation :: Sphinx
Classifier: Topic :: Software Development
Classifier: Topic :: Software Development :: Documentation
Classifier: Topic :: Text Processing :: Markup :: reStructuredText
Requires-Python: >=3.10
Requires-Dist: atsphinx-helper
Requires-Dist: beautifulsoup4
Requires-Dist: lxml
Requires-Dist: sphinx
